Workbook

Sheet PAGO A J.O
B4: PABLO FRANCISCONO | E4: JUNIO | H4: VALOR DE METRO VEREDAS | K4: honorario pablo
B5: TIPO DE FRENTE | C5: M2 | D5: PU ($) | E5: TOTAL ($) | H5: APROBADO 30/01/2026 | J5: APROBADO 23/05/26 | K5: 1911217
B6: HONORARIOS | C6: =+'M2 EJECUTADOS '!E5 -> 2316.4 | D6: 600 | E6: =D6*C6 -> 1389840 | H6: HONORARIOS | I6: 500 | J6: Si supera los 2200 cobra 3400
B7: CUADRILLA | C7: =C6 -> 2316.4 | D7: 2800 | E7: =D7*C7 -> 6485920 | H7: CUADRILLA | I7: 2400
B8: DESCUENTO REPARACION DE MAQUINARIA Y MAT- | E8: -100000 | H8: TOTAL M2 | I8: 2900
B9: PAGO TOTAL | E9: =SUM(E6:E8) -> 7775760
B11: SERGIO ARENA | E11: JUNIO | H11: VALOR DE METRO VEREDAS
B12: TIPO DE FRENTE | C12: M2 | D12: PU ($) | E12: TOTAL ($) | H12: 45717 | I12: 11000
B13: COLOCACION Y HORMIGON | C13: =+'M2 EJECUTADOS '!E6 -> 1512.2 | D13: 20000 | E13: =C13*D13 -> 30244000 | H13: 45748 | I13: 12000
B14: FRENTE PENDIENTE: Jonte 3861 | C14: 86.2 | D14: 20000 | E14: =C14*D14 -> 1724000
B15: FRENTE PENDIENTE: Marcos sastre 2643 | C15: 46.16 | D15: 20000 | E15: =C15*D15 -> 923200 | H15: 45870 | I15: 16000
B16: SUBTOTAL | E16: =SUM(E13:E15) -> 32891200 | H16: 46113 | I16: 20000 | J16: Se descuenta total combustible | K16: consumo | L16: tope | M16: saldo
B17: DESCUENTO REPARACION DE MAQUINARIA Y MAT | E17: =+'SA Descuento'!J5 -> 56400 | H17: 46143 | I17: 20000 | J17: tope 500mil combustible | K17: 745003 | L17: 500000 | M17: =+K17-L17 -> 245003
B18: DESCUENTO ANTICIPO 03-07-2026 | E18: 5000000
B19: DESCUENTO COMBUSTIBLE | E19: 245003 | J19: 260 camiones
B20: DESCUENTO DE FRENTE: EMPEDRADO 2492 | C20: 34.5 | D20: 20000 | E20: =+D20*C20 -> 690000
B21: DESCUENTO SUELDOS | E21: =+'S.A SUELDO DEPOSITADO'!R12 -> 8546494
B22: SUBTOTAL DESCUENTO | E22: =-SUM(E17:E21) -> -14537897
B23: PAGO TOTAL | E23: =+E16+E22 -> 18353303
B25: SAMOEL CASTILLO | E25: JUNIO | H25: VALOR DE METRO VEREDAS
B26: TIPO DE FRENTE | C26: M2 | D26: PU ($) | E26: TOTAL ($) | H26: APROBADO 01/01/2026
B27: COLOCACION Y HORMIGON | C27: =+'M2 EJECUTADOS '!E7 -> 1766.3 | D27: 20000 | E27: =C27*D27 -> 35326000 | H27: TOTAL M2 | I27: 20000
B28: FRENTES PENDIENTE: EMPEDRADO 2492 | C28: 34.5 | D28: 20000 | E28: =+D28*C28 -> 690000
B29: SUBTOTAL | E29: =SUM(E27) -> 35326000
B30: DESCUENTO CAMION | E30: 3600000
B31: DESCUENTO COMBUSTIBLE | E31: 820000
B32: DESCUENTO REPARACION DE MAQUINARIA Y MAT | E32: 0
B33: DESCUENTO ANTICIPO | E33: 0
B34: DESCUENTO SUELDOS | E34: =+'SC. SUELDOS DEPOSITADOS'!R11 -> 8372262
B35: SUBTOTAL DESCUENTO | E35: =-SUM(E30:E34) -> -12792262
B36: PAGO TOTAL | E36: =+E29+E35 -> 22533738

Sheet P.F SUELDO DEPOSITADO
A1: Legajo | B1: Apellido | C1: Nombre/s | D1: C.U.I.L. | E1: Sucursal | F1: Sección | G1: Servicio | H1: Zona de pago | I1: Supervisor | J1: Ingreso | K1: Egreso | L1: Categoría | M1: MENSUALES | N1: 1° QUINCENA | O1: 2° QUINCENA | P1: SAC | Q1: FINALES | R1: AJUSTES
A2: 5037 | B2: CARABAJAL | C2: SANTIAGO AGUSTIN | D2: 20-42928145-9 | E2: CENTRAL | F2: UOCRA VEREDAS | H2: UOCRA QUINCENA | I2: PABLO FRANCISCONO | J2: 45736 | L2: UOCRA OFICIAL ESPEC. | N2: 644080 | O2: 486695 | P2: 553109
A3: 5081 | B3: ROSANO | C3: FERNANDO MARTIN | D3: 20-37067183-5 | E3: CENTRAL | F3: UOCRA VEREDAS | H3: UOCRA QUINCENA | I3: PABLO FRANCISCONO | J3: 45750 | L3: UOCRA OFICIAL ESPEC. | N3: 644080 | O3: 464585 | P3: 553109
A4: 5273 | B4: RIVAS CABALLERO | C4: JOSE MANUEL | D4: 20-95108572-4 | E4: CENTRAL | F4: UOCRA VEREDAS | H4: UOCRA QUINCENA | I4: PABLO FRANCISCONO | J4: 45817 | L4: UOCRA OFICIAL ESPEC. | N4: 644080 | O4: 652373 | P4: 553109
A5: 5393 | B5: ROMERO | C5: ROBERTO RAMON | D5: 20-35341843-3 | E5: CENTRAL | F5: UOCRA VEREDAS | H5: UOCRA QUINCENA | I5: PABLO FRANCISCONO | J5: 45860 | L5: UOCRA OFICIAL ESPEC. | N5: 644080 | O5: 652373 | P5: 553109
A6: 5433 | B6: MEZA | C6: JORGE RUBEN | D6: 20-27138368-2 | E6: CENTRAL | F6: UOCRA VEREDAS | H6: UOCRA QUINCENA | I6: PABLO FRANCISCONO | J6: 45870 | L6: UOCRA OFICIAL ESPEC. | N6: 644080 | O6: 530914 | P6: 553109
A7: 5601 | B7: RODRIGUEZ | C7: ALFREDO ROQUE | D7: 20-26736333-2 | E7: CENTRAL | F7: UOCRA VEREDAS | H7: UOCRA QUINCENA | I7: PABLO FRANCISCONO | J7: 45947 | L7: UOCRA OFICIAL | N7: 553043 | O7: 557593 | P7: 473147
A8: 5982 | B8: RODRIGUEZ | C8: LEONARDO OSCAR | D8: 20-33144430-9 | E8: CENTRAL | F8: UOCRA VEREDAS | G8: UOCRA VEREDAS | H8: UOCRA QUINCENA | I8: PABLO FRANCISCONO | J8: 45980 | L8: UOCRA OFICIAL | N8: 553043 | O8: 557593 | P8: 473147
A9: 5983 | B9: MANUEL | C9: DANIEL ALBERTO | D9: 20-40006052-6 | E9: CENTRAL | F9: UOCRA VEREDAS | G9: UOCRA VEREDAS | H9: UOCRA QUINCENA | I9: PABLO FRANCISCONO | J9: 45980 | L9: UOCRA OFICIAL ESPEC. | N9: 644080 | O9: 652373 | P9: 553109
A10: 6115 | B10: RODRIGUEZ | C10: SANTIAGO ISMAEL | D10: 20-43796730-0 | E10: CENTRAL | F10: UOCRA VEREDAS | H10: UOCRA QUINCENA | I10: PABLO FRANCISCONO | J10: 46059 | L10: UOCRA OFICIAL | N10: 553043 | O10: 557593 | P10: 379040
A11: 6116 | B11: RODRIGUEZ | C11: LAUTARO ABEL | D11: 20-42053599-7 | E11: CENTRAL | F11: UOCRA VEREDAS | H11: UOCRA QUINCENA | I11: PABLO FRANCISCONO | J11: 46059 | L11: UOCRA OFICIAL | N11: 433843 | O11: 557593 | P11: 379040
A12: 6127 | B12: CARABAJAL | C12: RENE ALBERTO | D12: 20-31509898-0 | E12: CENTRAL | F12: UOCRA VEREDAS | H12: UOCRA QUINCENA | I12: PABLO FRANCISCONO | J12: 46076 | L12: UOCRA OFICIAL ESPEC. | N12: 644080 | O12: 652373 | P12: 391149
A13: 6128 | B13: CARABAJAL | C13: ARNALDO GASTON | D13: 20-38717013-9 | E13: CENTRAL | F13: UOCRA VEREDAS | H13: UOCRA QUINCENA | I13: PABLO FRANCISCONO | J13: 46076 | L13: UOCRA OFICIAL ESPEC. | N13: 644080 | O13: 652373 | P13: 391149
A14: 6129 | B14: CARABAJAL | C14: ELIAS MARIANO | D14: 23-45159147-9 | E14: CENTRAL | F14: UOCRA VEREDAS | H14: UOCRA QUINCENA | I14: PABLO FRANCISCONO | J14: 46076 | L14: UOCRA OFICIAL ESPEC. | N14: 644080 | O14: 508804 | P14: 391149
A15: 6234 | B15: SILVA | C15: CRISTIAN MAURICIO | D15: 20-30650248-5 | E15: CENTRAL | F15: UOCRA VEREDAS | H15: UOCRA QUINCENA | I15: PABLO FRANCISCONO | J15: 46139 | L15: UOCRA OFICIAL ESPEC. | N15: 501897 | O15: 505738 | P15: 152129
A16: 6235 | B16: GARCIA CRUZ | C16: OMAR MISAEL | D16: 20-95346650-4 | E16: CENTRAL | F16: UOCRA VEREDAS | H16: UOCRA QUINCENA | I16: PABLO FRANCISCONO | J16: 46139 | L16: UOCRA OFICIAL ESPEC. | N16: 644080 | O16: 530914 | P16: 197927
A17: 6244 | B17: OLGUIN MAMANI | C17: RAUL | D17: 20-94679033-9 | E17: CENTRAL | F17: UOCRA VEREDAS | H17: UOCRA QUINCENA | I17: PABLO FRANCISCONO | J17: 46150 | L17: UOCRA OFICIAL | N17: 549804 | O17: 432074 | P17: 98570

Sheet S.A SUELDO DEPOSITADO
A1: Legajo | B1: Apellido | C1: Nombre/s | D1: C.U.I.L. | E1: Sucursal | F1: Sección | G1: Servicio | H1: Zona de pago | I1: Supervisor | J1: Ingreso | K1: Egreso | L1: Categoría | M1: MENSUALES | N1: 1° QUINCENA | O1: 2° QUINCENA | P1: SAC | Q1: FINALES | R1: AJUSTES
A2: 1705 | B2: CHAMBI VEDIA | C2: FRANCISCO | D2: 20-93861478-5 | E2: CENTRAL | F2: UOCRA VEREDAS | H2: UOCRA QUINCENA | I2: SERGIO ARENA | J2: 44630 | L2: UOCRA OFICIAL | N2: 549804 | O2: 554216 | P2: 490095
A3: 1708 | B3: RODRIGUEZ ROCHA | C3: RAUL EDUARDO | D3: 20-94486916-7 | E3: CENTRAL | F3: UOCRA VEREDAS | H3: UOCRA QUINCENA | I3: SERGIO ARENA | J3: 44630 | L3: UOCRA OFICIAL | N3: 549804 | O3: 554216 | P3: 490095
A4: 2348 | B4: FERNANDEZ LOPEZ | C4: CASIMIRO | D4: 20-94788169-9 | E4: CENTRAL | F4: UOCRA VEREDAS | H4: UOCRA QUINCENA | I4: SERGIO ARENA | J4: 45030 | L4: UOCRA OFICIAL ESPEC. | N4: 640293 | O4: 648427 | P4: 572921
A5: 4888 | B5: CASTILLO | C5: LEANDRO MISAEL | D5: 20-44129001-3 | E5: CENTRAL | F5: UOCRA VEREDAS | H5: UOCRA QUINCENA | I5: SERGIO ARENA | J5: 45705 | L5: UOCRA OFICIAL | N5: 553043 | O5: 418194 | P5: 471527
A6: 4903 | B6: RODRIGUEZ CHAVEZ | C6: MOISES | D6: 20-96034749-9 | E6: CENTRAL | F6: UOCRA VEREDAS | H6: UOCRA QUINCENA | I6: SERGIO ARENA | J6: 45708 | L6: UOCRA OFICIAL | N6: 549804 | O6: 554216 | P6: 468617
A7: 5376 | B7: CHAMBI MAMANI | C7: JONAS WALTER | D7: 20-93864483-8 | E7: CENTRAL | F7: UOCRA VEREDAS | H7: UOCRA QUINCENA | I7: SERGIO ARENA | J7: 45849 | L7: UOCRA OFICIAL | N7: 553043 | O7: 557593 | P7: 493139
A8: 6057 | B8: FERNANDEZ ROJAS | C8: JHOEL | D8: 20-95338010-3 | E8: CENTRAL | F8: UOCRA VEREDAS | H8: UOCRA QUINCENA | I8: SERGIO ARENA | J8: 46034 | L8: UOCRA OFICIAL | N8: 553043 | O8: 557593 | P8: 463169
A9: 6149 | B9: ARANDA | C9: WALTER GUSTAVO | D9: 20-25639074-5 | E9: CENTRAL | F9: UOCRA VEREDAS | G9: UOCRA VEREDAS | H9: UOCRA QUINCENA | I9: SERGIO ARENA | J9: 46084 | L9: UOCRA OFICIAL ESPEC. | N9: 640293 | O9: 648427 | P9: 379837
A10: 6249 | B10: TORRICO ROJAS | C10: JHON CLAUDIO | D10: 20-95095576-8 | E10: CENTRAL | F10: UOCRA VEREDAS | H10: UOCRA QUINCENA | I10: SERGIO ARENA | J10: 46160 | L10: UOCRA AYUDANTE | N10: 470766 | O10: 472002 | P10: 38572
A11: 6260 | B11: HUARACHI CAMACHO | C11: LUIS FERNANDO | D11: 23-94933010-9 | E11: CENTRAL | F11: UOCRA VEREDAS | H11: UOCRA QUINCENA | I11: SERGIO ARENA | J11: 46197 | L11: UOCRA AYUDANTE | O11: 177607
N12: =SUM(N2:N11) -> 5059893 | O12: =SUM(O2:O11) -> 5142491 | R12: =+O12+N13 -> 8546494
N13: =+N12-1655890 -> 3404003

Sheet SC. SUELDOS DEPOSITADOS
A1: Legajo | B1: Apellido | C1: Nombre/s | D1: C.U.I.L. | E1: Sucursal | F1: Sección | G1: Servicio | H1: Zona de pago | I1: Supervisor | J1: Ingreso | K1: Egreso | L1: Categoría | M1: MENSUALES | N1: 1° QUINCENA | O1: 2° QUINCENA | P1: SAC | Q1: FINALES | R1: AJUSTES
A2: 4508 | B2: CUTIPA SAAVEDRA | C2: AGUSTIN | D2: 20-94418646-9 | E2: CENTRAL | F2: UOCRA VEREDAS | H2: UOCRA QUINCENA | I2: CASTILLO SAMOEL | J2: 45566 | L2: UOCRA OFICIAL ESPEC. | N2: 240539 | O2: 652373 | P2: 546690
A3: 4885 | B3: CASTILLO QUISPE | C3: SAMOEL | D3: 20-94175481-4 | E3: CENTRAL | F3: UOCRA VEREDAS | H3: UOCRA QUINCENA | I3: CASTILLO SAMOEL | J3: 45705 | L3: UOCRA ESPECIALIZADO CAPATAZ | N3: 872048 | O3: 872048 | P3: 840399
A4: 4993 | B4: CARABAJAL | C4: MATIAS EMANUEL | D4: 20-32386061-1 | E4: CENTRAL | F4: UOCRA VEREDAS | H4: UOCRA QUINCENA | I4: CASTILLO SAMOEL | J4: 45721 | L4: UOCRA OFICIAL ESPEC. | N4: 196320 | O4: 652373 | P4: 546690
A5: 4995 | B5: CHOQUEHUANCA QUISPE | C5: BRIAN ADEMAR | D5: 20-94400384-4 | E5: CENTRAL | F5: UOCRA VEREDAS | H5: UOCRA QUINCENA | I5: CASTILLO SAMOEL | J5: 45721 | L5: UOCRA OFICIAL ESPEC. | N5: 195254 | O5: 571155 | P5: 514855
A6: 5072 | B6: ORTIZ | C6: JORGE EMANUEL | D6: 20-38188815-1 | E6: CENTRAL | F6: UOCRA VEREDAS | H6: UOCRA QUINCENA | I6: CASTILLO SAMOEL | J6: 45750 | L6: UOCRA OFICIAL | N6: 169500 | O6: 557593 | P6: 457534
A7: 5474 | B7: CAJAL | C7: MIGUEL ENRIQUE | D7: 20-17862426-2 | E7: CENTRAL | F7: UOCRA VEREDAS | H7: UOCRA QUINCENA | I7: CASTILLO SAMOEL | J7: 45889 | L7: UOCRA OFICIAL ESPEC, CHOFER | N7: 492687 | O7: 516969 | P7: 559591
A8: 5987 | B8: RODRIGUEZ ALCOSER | C8: EUDES | D8: 20-94319437-9 | E8: CENTRAL | F8: UOCRA VEREDAS | H8: UOCRA QUINCENA | I8: CASTILLO SAMOEL | J8: 45988 | L8: UOCRA OFICIAL ESPEC. | N8: 262649 | O8: 652373 | P8: 546690
A9: 6074 | B9: RODRIGUEZ VILLAROEL | C9: VLADIMIR | D9: 20-94524936-7 | E9: CENTRAL | F9: UOCRA VEREDAS | H9: UOCRA QUINCENA | I9: CASTILLO SAMOEL | J9: 46041 | L9: UOCRA OFICIAL | N9: 264245 | O9: 468900 | P9: 412034
A10: 6075 | B10: SANCHEZ | C10: EMILIO CEFERINO | D10: 20-21338680-9 | E10: CENTRAL | F10: UOCRA VEREDAS | H10: UOCRA QUINCENA | I10: CASTILLO SAMOEL | J10: 46041 | L10: UOCRA OFICIAL | N10: 225092 | O10: 510144 | P10: 418598
N11: =SUM(N2:N10) -> 2918334 | O11: =SUM(O2:O10) -> 5453928 | R11: =SUM(N11:Q11) -> 8372262

Sheet M2 EJECUTADOS 
B3: MES ACTUAL
B4: JEFE DE OBRA | C4: COLOCACION | D4: HORMIGON | E4: TOTAL M. OPERATIVOS
B5: Pablo Franciscono | C5: =SUMIFS('P.F FRENTES'!C:C,'P.F FRENTES'!F:F,C4) -> 1751 | D5: =SUMIFS('P.F FRENTES'!C:C,'P.F FRENTES'!F:F,D4) -> 565.4 | E5: =C5+D5 -> 2316.4
B6: Sergio Arena | C6: =SUMIFS('S.A FRENTES'!C:C,'S.A FRENTES'!F:F,C4) -> 1208.1 | D6: =SUMIFS('S.A FRENTES'!C:C,'S.A FRENTES'!F:F,D4) -> 304.1 | E6: =C6+D6 -> 1512.2
B7: Samoel | C7: =SUMIFS('S.C FRENTES'!$C:$C,'S.C FRENTES'!$F:$F,'M2 EJECUTADOS '!C4) -> 1652.1 | D7: =SUMIFS('S.C FRENTES'!$C:$C,'S.C FRENTES'!$F:$F,'M2 EJECUTADOS '!D4) -> 114.2 | E7: =C7+D7 -> 1766.3
B8: TOTAL | E8: =SUM(E5:E7) -> 5594.9

Sheet P.F FRENTES
A1: Calle | B1: Altura | C1: M2 EJECUTADOS | D1: Estado | E1: Intervención | F1: MATERIALIDAD
A2: ALLENDE | B2: 4544 | C2: 41.7 | D2: CERTIFICADO 34 | E2: COMPLETO | F2: COLOCACION
A3: ASUNCION | B3: 4514 | C3: 46.4 | D3: CERTIFICADO 34 | E3: COMPLETO | F3: COLOCACION
A4: BACON | B4: 5459 | C4: 28.8 | D4: CERTIFICADO 34 | E4: PARCIAL | F4: COLOCACION
A5: BACON | B5: 5475 | C5: 28.9 | D5: CERTIFICADO 34 | E5: COMPLETO | F5: COLOCACION
A6: BAZURCO | B6: 3520 | C6: 32.6 | D6: CERTIFICADO 34 | E6: COMPLETO | F6: COLOCACION
A7: CABEZON, JOSE LEON | B7: 3540 | C7: 43.7 | D7: CERTIFICADO 34 | E7: COMPLETO | F7: COLOCACION
A8: CABEZON, JOSE LEON | B8: 3548 | C8: 121.3 | D8: CERTIFICADO 34 | E8: COMPLETO | F8: COLOCACION
A9: CABEZON, JOSE LEON | B9: 3568 | C9: 45.9 | D9: CERTIFICADO 34 | E9: COMPLETO | F9: COLOCACION
A10: CANTILO, JOSE LUIS | B10: 4602 | C10: 187 | D10: CERTIFICADO 34 | E10: PARCIAL | F10: HORMIGON
A11: CANTILO, JOSE LUIS | B11: 5040 | C11: 44.4 | D11: CERTIFICADO 34 | E11: COMPLETO | F11: COLOCACION
A12: CANTILO, JOSE LUIS | B12: 5149 | C12: 42.3 | D12: CERTIFICADO 34 | E12: PARCIAL | F12: COLOCACION
A13: CONCORDIA | B13: 3624 | C13: 73.3 | D13: CERTIFICADO 34 | E13: COMPLETO | F13: COLOCACION
... A40: VALLEJOS | B40: 4267 | C40: 40.2 | D40: CERTIFICADO 34 | E40: COMPLETO | F40: COLOCACION

Sheet S.A FRENTES
A1: Calle | B1: Altura | C1: M2 EJECUTADOS | D1: Estado | E1: Intervención | F1: MATERIALIDAD
A2: ARGERICH | B2: 2802 | C2: 148.7 | D2: CERTIFICADO 34 | E2: COMPLETO | F2: COLOCACION
A3: BAIGORRIA | B3: 3020 | C3: 37.3 | D3: CERTIFICADO 34 | E3: COMPLETO | F3: COLOCACION
A4: CHIVILCOY AV. | B4: 2593 | C4: 33.1 | D4: CERTIFICADO 34 | E4: COMPLETO | F4: COLOCACION
A5: CONDARCO | B5: 2766 | C5: 36.3 | D5: CERTIFICADO 34 | E5: COMPLETO | F5: COLOCACION
A6: ESTADO PLURINACIONAL DE BOLIVIA | B6: 2785 | C6: 38.7 | D6: CERTIFICADO 34 | E6: PARCIAL | F6: COLOCACION
A7: GUALEGUAYCHU | B7: 3126 | C7: 41 | D7: CERTIFICADO 34 | E7: COMPLETO | F7: COLOCACION
A8: GUTIERREZ, RICARDO | B8: 2642 | C8: 46.6 | D8: CERTIFICADO 34 | E8: COMPLETO | F8: COLOCACION
A9: GUTIERREZ, RICARDO | B9: 3900 | C9: 85.4 | D9: CERTIFICADO 34 | E9: PARCIAL | F9: HORMIGON
A10: HELGUERA | B10: 2502 | C10: 53.9 | D10: CERTIFICADO 34 | E10: PARCIAL | F10: COLOCACION
A11: JUAREZ, BENITO | B11: 3354 | C11: 44.1 | D11: CERTIFICADO 34 | E11: COMPLETO | F11: COLOCACION
A12: LOZANO, PEDRO | B12: 5204 | C12: 55.7 | D12: CERTIFICADO 34 | E12: PARCIAL | F12: HORMIGON
A13: MELINCUE | B13: 2476 | C13: 46.7 | D13: CERTIFICADO 34 | E13: PARCIAL | F13: COLOCACION
... A25: VARELA, JOSE PEDRO | B25: 5170 | C25: 93.4 | D25: CERTIFICADO 34 | E25: COMPLETO | F25: COLOCACION

Sheet S.C FRENTES
A1: Calle | B1: Altura | C1: M2 EJECUTADOS | D1: Estado | E1: Intervención | F1: MATERIALIDAD
A2: ALVAREZ JONTE | B2: 2028 | C2: 31.5 | D2: CERTIFICADO 34 | E2: COMPLETO | F2: COLOCACION
A3: ALVAREZ JONTE AV. | B3: 2020 | C3: 4 | D3: CERTIFICADO 34 | E3: PARCIAL | F3: COLOCACION
A4: ALVAREZ JONTE AV. | B4: 2443 | C4: 30.1 | D4: CERTIFICADO 34 | E4: PARCIAL | F4: COLOCACION
A5: ALVAREZ JONTE AV. | B5: 2621 | C5: 41.6 | D5: CERTIFICADO 34 | E5: COMPLETO | F5: COLOCACION
A6: ALVAREZ JONTE AV. | B6: 3709 | C6: 40.7 | D6: CERTIFICADO 34 | E6: PARCIAL | F6: COLOCACION
A7: ALVAREZ JONTE AV. | B7: 3758 | C7: 32.4 | D7: CERTIFICADO 34 | E7: COMPLETO | F7: COLOCACION
A8: ALVAREZ JONTE AV. | B8: 3776 | C8: 31 | D8: CERTIFICADO 34 | E8: COMPLETO | F8: COLOCACION
A9: ARREGUI | B9: 2391 | C9: 44.3 | D9: CERTIFICADO 34 | E9: PARCIAL | F9: COLOCACION
A10: ARREGUI AV. | B10: 2485 | C10: 44.6 | D10: CERTIFICADO 34 | E10: COMPLETO | F10: COLOCACION
A11: BUFANO, ALFREDO R. | B11: 1912 | C11: 47.4 | D11: CERTIFICADO 34 | E11: COMPLETO | F11: COLOCACION
A12: BUFANO, ALFREDO R. | B12: 2466 | C12: 32.1 | D12: CERTIFICADO 34 | E12: COMPLETO | F12: COLOCACION
A13: BUFANO, ALFREDO R. | B13: 2476 | C13: 8.3 | D13: CERTIFICADO 34 | E13: PARCIAL | F13: HORMIGON
... A49: VILARDEBO, TEODORO | B49: 2124 | C49: 88.8 | D49: CERTIFICADO 34 | E49: PARCIAL | F49: COLOCACION

Sheet SA Descuento
A1: Fecha | B1: Jefe de Obra | C1: Obra | D1: Tipo | E1: Remito | F1: Item | G1: Unidad | H1: Cantidad | I1: unitario | J1: parcial
A2: 46198 | B2: Sergio Arena | C2: VEREDAS | D2: RETIRO | E2: N09522 | F2: CABO P/ESCOBILLON | G2: unid | H2: 3 | I2: 6000 | J2: =+I2*H2 -> 18000
A3: 46199 | B3: Sergio Arena | C3: VEREDAS | D3: RETIRO | E3: N09535 | F3: DISCO DE CORTE HIERRO 9" | G3: unid | H3: 1 | I3: 10400 | J3: =+I3*H3 -> 10400
A4: 46203 | B4: Sergio Arena | C4: VEREDAS | D4: RETIRO | E4: N09566 | F4: DISCO DE VIDIA 9" | G4: unid | H4: 1 | I4: 28000 | J4: =+I4*H4 -> 28000
J5: =SUM(J2:J4) -> 56400
A14: reparaciones mayo
A15: ID | B15: Fecha | C15: Ingreso / Egreso | D15: Descripcion
A16: GRUPO SENSEI 1 | B16: 46175 | C16: I | D16: GRUPO SENSEI INGRESA PARA REPARACION. DESOLDADO. RM00474 MEDIO
A17: GRUPO SENSEI | B17: 46177 | C17: I | D17: GRUPO SENSEI A REVISAR. RM00478 MEDIO
A18: T3 | B18: 46177 | C18: E | D18: GRUPO SENSEI SE REALIZO SOLDADURA DE RUEDA. RM00478 MEDIO
A19: MARTILLO BOSCH | B19: 46182 | C19: E | D19: GRUPO SENSEI SE REALIZO LIMPIEZA DEL CARBURADOR RM00482
A20: T3 | B20: 46182 | C20: E | D20: GRUPO SENSEI SE REALIZO SOLDADURA DE RUEDA RM00482
A21: MARTILLO BOSCH | B21: 46182 | C21: E | D21: GRUPO SENSEI RETIRA RM00482
A22: AMOLADORA BOSCH | B22: 46184 | C22: E | D22: TE3 RETIRA A PRESTAMO RM00487 BUENO
A23: GRUPO SENSEI | B23: 46185 | C23: I | D23: TE3 DEVOLUCION DE PRESTAMO RM00488 BUENO
A24: GRUPO SENSEI | B24: 46189 | C24: E | D24: T7 RETIRA A PRESTAMO. FUNCIONANDO. Y UN ALARGUE RM00494 BUENO
A25: GRUPO SENSEI CHICO | B25: 46190 | C25: I | D25: T7 DEVOLUCION DE PERCUTOR COMPLETO FUNCIONANDO. RM00495 BUENO
A26: GRUPO SHIMURA | B26: 46191 | C26: I | D26: AMOLADORA BOSCH A REVISAR RM00500 MEDIO
A27: AMOLADORA BOSCH | B27: 46192 | C27: E | D27: AMOLADORA BOSCH SE AJUSTARON LOS TORNILLOS RM00501 MEDIO
B28: 46192 | C28: I | D28: MARTILLO BOSCH A REVISAR RM00502 MEDIO

Sheet P.F DESCUENTOS
A1: reparacionesJUNIO
A2: Fecha | B2: Ingreso / Egreso | C2: Descripcion
A3: 46183 | B3: E | C3: KLD1 SE PUSIERON RUEDAS NUEVAS, BUJIA Y ACEITE Y FILTRO DE AIRE RM00485 MAL USO GRAVE (A DESCONTAR)
A4: 46183 | B4: E | C4: KLD2 SE SOLDO SOPORTE DE RUEDAS, BUJIA Y FILTRO DE AIRE. ACEITE. RM00485 MAL USO GRAVE (A DESCONTAR)
